    <character>
        <cnm>5508865</cnm>
        <unm>2863408</unm>
        <unn></unn>
        <cls>37</cls>
        <crd>5</crd>
        <ast>3705</ast>
        <l2d>false</l2d>
        <ehx>0</ehx>
        <ddm>1628794565000</ddm>
        <cpt>3</cpt>
        <rpc>20</rpc>
        <rwc>1</rwc>
        <npc>13</npc>
        <nwc>5</nwc>
        <tnm>0</tnm>
        <psi>0</psi>
        <pmn>0</pmn>
        <pfr>0</pfr>
        <psd>0</psd>
        <hst>false</hst>
        <ctt>1</ctt>
        <nrs>0</nrs>
    </character>
    <characterSkins>
        <unm>2863408</unm>
        <cls>37</cls>
        <ckt>3701</ckt>
        <own>true</own>
        <live>false</live>
        <setp>1</setp>
    </characterSkins>
    <characterSkins>
        <unm>2863408</unm>
        <cls>37</cls>
        <ckt>3705</ckt>
        <own>true</own>
        <live>true</live>
        <setp>1</setp>
    </characterSkins>
    <characterSkins>
        <unm>2863408</unm>
        <cls>37</cls>
        <ckt>3707</ckt>
        <own>true</own>
        <live>true</live>
        <setp>1</setp>
    </characterSkins>
    <characterSkins>
        <unm>2863408</unm>
        <cls>37</cls>
        <ckt>3708</ckt>
        <own>true</own>
        <live>true</live>
        <setp>1</setp>
    </characterSkins>
    <characterSkins>
        <unm>0</unm>
        <cls>37</cls>
        <ckt>3710</ckt>
        <own>false</own>
        <live>false</live>
        <setp>1</setp>
    </characterSkins>
    <characterSkins>
        <unm>0</unm>
        <cls>37</cls>
        <ckt>3704</ckt>
        <own>false</own>
        <live>false</live>
        <setp>1</setp>
    </characterSkins>
    <characterSkins>
        <unm>0</unm>
        <cls>37</cls>
        <ckt>3706</ckt>
        <own>false</own>
        <live>false</live>
        <setp>1</setp>
    </characterSkins>
    <characterSkins>
        <unm>0</unm>
        <cls>37</cls>
        <ckt>3709</ckt>
        <own>false</own>
        <live>false</live>
        <setp>1</setp>
    </characterSkins>
    <characterSkins>
        <unm>0</unm>
        <cls>37</cls>
        <ckt>3702</ckt>
        <own>false</own>
        <live>false</live>
        <setp>1</setp>
    </characterSkins>
    <characterSkins>
        <unm>0</unm>
        <cls>37</cls>
        <ckt>3703</ckt>
        <own>false</own>
        <live>false</live>
        <setp>1</setp>
    </characterSkins>
    <characterDocument>
        <unm>2863408</unm>
        <cls>37</cls>
        <ptt>3</ptt>
        <ptn>false</ptn>
        <wkn>0</wkn>
        <wks>false</wks>
        <crl>19</crl>
        <lik>false</lik>
        <itv>0</itv>
        <itr>false</itr>
    </characterDocument>
    <characterSignatureList>
        <unm>2863408</unm>
        <cc>37</cc>
        <ats>101</ats>
        <att>101</att>
        <lv>0</lv>
    </characterSignatureList>
    <characterSignatureList>
        <unm>2863408</unm>
        <cc>37</cc>
        <ats>101</ats>
        <att>201</att>
        <lv>0</lv>
    </characterSignatureList>
    <characterSignatureList>
        <unm>2863408</unm>
        <cc>37</cc>
        <ats>101</ats>
        <att>301</att>
        <lv>0</lv>
    </characterSignatureList>
    <characterSignatureList>
        <unm>2863408</unm>
        <cc>37</cc>
        <ats>101</ats>
        <att>401</att>
        <lv>0</lv>
    </characterSignatureList>